mod_wsgi_van/__init__.py
mod_wsgi_van/router.py
mod_wsgi_van/server.py
mod_wsgi_van-1.0.0.dist-info/METADATA
mod_wsgi_van-1.0.0.dist-info/WHEEL
mod_wsgi_van-1.0.0.dist-info/licenses/LICENSE
mod_wsgi_van-1.0.0.dist-info/RECORD
