Metadata-Version: 2.1
Name: mod-wsgi-van
Version: 1.0.0
Summary: Dynamically route mod_wsgi to mod_vhost_alias
Project-URL: Homepage, https://github.com/deckar01/mod-wsgi-van
Project-URL: Bug Tracker, https://github.com/deckar01/mod-wsgi-van/issues
Author-email: Jared Deckard <jared@shademaps.com>
License-File: LICENSE
Classifier: License :: OSI Approved :: MIT License
Classifier: Operating System :: OS Independent
Classifier: Programming Language :: Python :: 3
Requires-Python: >=3.10
